gscompressor/__init__.py
gscompressor/compress.py
gscompressor/compressor.py
gscompressor/draco_decoder
gscompressor/draco_encoder
gscompressor/quantize.py
gscompressor/quantization/__init__.py
gscompressor/quantization/compressor.py
gscompressor/quantization/draco_decoder
gscompressor/quantization/draco_encoder
gscompressor-1.0.4.dist-info/METADATA
gscompressor-1.0.4.dist-info/WHEEL
gscompressor-1.0.4.dist-info/top_level.txt
gscompressor-1.0.4.dist-info/RECORD
