Metadata-Version: 2.4
Name: gscompressor
Version: 1.0.4
Summary: Refactored python training and inference code for 3D Gaussian Splatting
Home-page: https://github.com/yindaheng98/gscompressor
Author: yindaheng98
Author-email: yindaheng98@gmail.com
Classifier: Programming Language :: Python :: 3
Requires-Dist: gaussian-splatting
Requires-Dist: reduced-3dgs
Dynamic: author
Dynamic: author-email
Dynamic: classifier
Dynamic: description
Dynamic: description-content-type
Dynamic: home-page
Dynamic: requires-dist
Dynamic: summary
